skilletlib/__init__.py
skilletlib/exceptions.py
skilletlib/panoply.py
skilletlib/skilletLoader.py
skilletlib/assets/__init__.py
skilletlib/assets/panorama/baseline_81/.meta-cnc.yaml
skilletlib/assets/panorama/baseline_81/baseline_81.xml
skilletlib/assets/panorama/baseline_90/.meta-cnc.yaml
skilletlib/assets/panorama/baseline_90/baseline_90.xml
skilletlib/assets/panos/baseline_80/.meta-cnc.yaml
skilletlib/assets/panos/baseline_80/baseline_80.xml
skilletlib/assets/panos/baseline_81/.meta-cnc.yaml
skilletlib/assets/panos/baseline_81/baseline_81.xml
skilletlib/assets/panos/baseline_90/.meta-cnc.yaml
skilletlib/assets/panos/baseline_90/baseline_90.xml
skilletlib/assets/panos/baseline_91/.meta-cnc.yaml
skilletlib/assets/panos/baseline_91/baseline_91.xml
skilletlib/remotes/__init__.py
skilletlib/remotes/git.py
skilletlib/skillet/__init__.py
skilletlib/skillet/app.py
skilletlib/skillet/base.py
skilletlib/skillet/docker.py
skilletlib/skillet/pan_validation.py
skilletlib/skillet/panos.py
skilletlib/skillet/python3.py
skilletlib/skillet/rest.py
skilletlib/skillet/template.py
skilletlib/skillet/terraform.py
skilletlib/skillet/workflow.py
skilletlib/snippet/__init__.py
skilletlib/snippet/base.py
skilletlib/snippet/docker.py
skilletlib/snippet/pan_validation.py
skilletlib/snippet/panos.py
skilletlib/snippet/python3.py
skilletlib/snippet/rest.py
skilletlib/snippet/template.py
skilletlib/snippet/workflow.py
skilletlib/utils/__init__.py
skilletlib/utils/testing_utils.py
skilletlib-1.2.5.dist-info/LICENSE
skilletlib-1.2.5.dist-info/METADATA
skilletlib-1.2.5.dist-info/WHEEL
skilletlib-1.2.5.dist-info/top_level.txt
skilletlib-1.2.5.dist-info/RECORD
