Metadata-Version: 2.1
Name: skilletlib
Version: 1.2.5
Summary: Tools for working with PAN-OS Skillets in Python 3
Home-page: https://github.com/paloaltonetworks/skilletlib
Author: Nathan Embery
Author-email: nembery@paloaltonetworks.com
License: Apache 2.0
Platform: UNKNOWN
Classifier: Development Status :: 5 - Production/Stable
Classifier: Programming Language :: Python :: 3.6
Classifier: Programming Language :: Python :: 3.7
Requires-Python: >=3.6
License-File: LICENSE
Requires-Dist: oyaml
Requires-Dist: docker
Requires-Dist: pan-python
Requires-Dist: jinja2 (==3.0.1)
Requires-Dist: pyyaml
Requires-Dist: xmldiff
Requires-Dist: xmltodict
Requires-Dist: requests-toolbelt
Requires-Dist: requests
Requires-Dist: jsonpath-ng
Requires-Dist: passlib
Requires-Dist: GitPython
Requires-Dist: jinja2-ansible-filters
Requires-Dist: jmespath
